mutwo/music_converters/__init__.py
mutwo/music_converters/configurations.py
mutwo/music_converters/constants.py
mutwo/music_converters/grace_notes.py
mutwo/music_converters/loudness.py
mutwo/music_converters/metricities.py
mutwo/music_converters/parsers.py
mutwo/music_converters/pitches.py
mutwo/music_converters/playing_indicators.py
mutwo/music_converters/spectrals.py
mutwo/music_events/__init__.py
mutwo/music_events/configurations.py
mutwo/music_events/music.py
mutwo/music_generators/__init__.py
mutwo/music_generators/constants.py
mutwo/music_generators/wilson.py
mutwo/music_parameters/__init__.py
mutwo/music_parameters/abc.py
mutwo/music_parameters/ambituses.py
mutwo/music_parameters/commas.py
mutwo/music_parameters/notation_indicators.py
mutwo/music_parameters/pitch_intervals.py
mutwo/music_parameters/playing_indicators.py
mutwo/music_parameters/volumes.py
mutwo/music_parameters/configurations/__init__.py
mutwo/music_parameters/configurations/lyrics.py
mutwo/music_parameters/configurations/pitch_intervals.py
mutwo/music_parameters/configurations/pitches.py
mutwo/music_parameters/configurations/volumes.py
mutwo/music_parameters/constants/__init__.py
mutwo/music_parameters/constants/diatonic_pitch_classes.py
mutwo/music_parameters/constants/pitch_intervals.py
mutwo/music_parameters/constants/pitches.py
mutwo/music_parameters/constants/playing_indicators.py
mutwo/music_parameters/constants/volumes.py
mutwo/music_parameters/lyrics/__init__.py
mutwo/music_parameters/lyrics/text_based_lyrics.py
mutwo/music_parameters/pitches/CommonHarmonic.py
mutwo/music_parameters/pitches/DirectPitch.py
mutwo/music_parameters/pitches/EqualDividedOctavePitch.py
mutwo/music_parameters/pitches/JustIntonationPitch.py
mutwo/music_parameters/pitches/MidiPitch.py
mutwo/music_parameters/pitches/WesternPitch.py
mutwo/music_parameters/pitches/__init__.py
mutwo_third_party/pydsm/__init__.py
mutwo_third_party/pydsm/pydsm/__init__.py
mutwo_third_party/pydsm/pydsm/iso226.py
mutwo.ext_music-0.16.1.dist-info/LICENSE
mutwo.ext_music-0.16.1.dist-info/METADATA
mutwo.ext_music-0.16.1.dist-info/WHEEL
mutwo.ext_music-0.16.1.dist-info/top_level.txt
mutwo.ext_music-0.16.1.dist-info/RECORD
