Metadata-Version: 2.1
Name: mutwo.ext-music
Version: 0.16.1
Summary: music extension for event based framework for generative art
Home-page: https://github.com/mutwo-org/mutwo.ext-music
Author: Levin Eric Zimmermann
Author-email: levin.eric.zimmermann@posteo.eu
License: GPL
Project-URL: Documentation, https://mutwo.readthedocs.io/en/latest/
Requires-Python: >=3.9, <4
License-File: LICENSE
Requires-Dist: mutwo.ext-core (<0.60.0,>=0.59.0)
Requires-Dist: phonemizer (<4.0.0,>=3.1.1)
Requires-Dist: gradient-free-optimizers (<2.0.0,>=1.0.7)
Provides-Extra: testing
Requires-Dist: nose ; extra == 'testing'
Requires-Dist: coveralls ; extra == 'testing'
Requires-Dist: mutwo.ext-common-generators (<1.0.0,>=0.8.0) ; extra == 'testing'
